CHANGELOG.md
README.md
mongo_queries_manager/__init__.py
mongo_queries_manager/mongodb_queries_manager.py
mongo_queries_manager-1.0.0.dist-info/LICENSE
mongo_queries_manager-1.0.0.dist-info/WHEEL
mongo_queries_manager-1.0.0.dist-info/METADATA
mongo_queries_manager-1.0.0.dist-info/RECORD
