Metadata-Version: 2.1
Name: mongo-queries-manager
Version: 1.0.0
Summary: Convert query parameters from API urls to MongoDB queries !
Home-page: https://pypi.org/project/mongo-queries-manager/
License: MIT
Keywords: query,mongodb,motor,api,request,mongo-queries-manager
Author: Theo Dangla
Author-email: theodangla32@gmail.com
Maintainer: Theo Dangla
Maintainer-email: theodangla32@gmail.com
Requires-Python: >=3.7,<4.0
Classifier: Development Status :: 4 - Beta
Classifier: Environment :: Web Environment
Classifier: Intended Audience :: Developers
Classifier: Intended Audience :: Information Technology
Classifier: License :: OSI Approved :: MIT License
Classifier: Operating System :: OS Independent
Classifier: Programming Language :: Python :: 3
Classifier: Programming Language :: Python :: 3.7
Classifier: Programming Language :: Python :: 3.8
Classifier: Programming Language :: Python :: 3.9
Classifier: Programming Language :: Python :: 3.10
Classifier: Programming Language :: Python :: 3.11
Classifier: Programming Language :: Python :: 3.10
Classifier: Programming Language :: Python :: 3.11
Classifier: Programming Language :: Python :: 3.7
Classifier: Programming Language :: Python :: 3.8
Classifier: Programming Language :: Python :: 3.9
Classifier: Topic :: Database
Classifier: Topic :: System :: Networking
Provides-Extra: dateparser
Requires-Dist: dateparser (>=1.0.0,<2.0.0); extra == "dateparser"
Project-URL: Changelog, https://github.com/comic31/MongoDBQueriesManager/blob/main/CHANGELOG.md
Project-URL: Documentation, https://github.com/comic31/MongoDBQueriesManager
Project-URL: Repository, https://github.com/comic31/MongoDBQueriesManager
